dsize/__init__.py
dsize/__version__.py
dsize/dsize.py
dsize-0.1.0.dist-info/METADATA
dsize-0.1.0.dist-info/WHEEL
dsize-0.1.0.dist-info/entry_points.txt
dsize-0.1.0.dist-info/top_level.txt
dsize-0.1.0.dist-info/RECORD
